cellpose/__init__.py
cellpose/__main__.py
cellpose/core.py
cellpose/default_ops.py
cellpose/dynamics.py
cellpose/io.py
cellpose/metrics.py
cellpose/models.py
cellpose/plot.py
cellpose/resnet_torch.py
cellpose/test.py
cellpose/test_mkl.py
cellpose/transforms.py
cellpose/utils.py
cellpose/version.py
cellpose/contrib/__init__.py
cellpose/contrib/distributed_segmentation.py
cellpose/contrib/openvino_utils.py
registration/__init__.py
registration/bidiphase.py
registration/default_ops.py
registration/io.py
registration/metrics.py
registration/nonrigid.py
registration/register.py
registration/rigid.py
registration/utils.py
registration/version.py
registration/zalign.py
registration/io/__init__.py
registration/io/binary.py
registration/io/save.py
registration/io/server.py
registration/io/tiff.py
registration/io/utils.py
neuropixelai-1.0.dist-info/LICENSE
neuropixelai-1.0.dist-info/METADATA
neuropixelai-1.0.dist-info/WHEEL
neuropixelai-1.0.dist-info/top_level.txt
neuropixelai-1.0.dist-info/RECORD
