Metadata-Version: 2.1
Name: neuropixelai
Version: 1.0
Summary: A package for calcium image processing
Home-page: 
Author: LiLab
Author-email: dadadadasukede@gmail.com
Classifier: Programming Language :: Python :: 3
Classifier: License :: OSI Approved :: BSD License
Classifier: Operating System :: OS Independent
Requires-Python: >=3.6
License-File: LICENSE
